quantbacktest/_0_wrappers.py
quantbacktest/_1_data_preparation.py
quantbacktest/_2_strategy_execution.py
quantbacktest/_3_individual_metrics.py
quantbacktest/_3_performance_evaluation.py
quantbacktest/__init__.py
quantbacktest/__main__.py
quantbacktest/_helper_functions.py
quantbacktest/main.py
quantbacktest/assets/raw_itsa_data/.gitkeep
quantbacktest/assets/raw_itsa_data/20190717_itsa_tokenbase_top600_wtd301_token.csv
quantbacktest/assets/raw_itsa_data/20190717_itsa_tokenbase_top600_wtd302_token_daily.csv
quantbacktest/assets/raw_itsa_data/btc-usd-max-coingecko.csv
quantbacktest/assets/results/.gitkeep
quantbacktest/assets/strategy_tables/.gitkeep
quantbacktest/components/.gitkeep
quantbacktest/components/_0_wrappers.py
quantbacktest/components/_1_data_preparation.py
quantbacktest/components/_2_strategy_execution.py
quantbacktest/components/_3_individual_metrics.py
quantbacktest/components/_3_performance_evaluation.py
quantbacktest/components/_helper_functions.py
quantbacktest-0.0.33.dist-info/LICENSE
quantbacktest-0.0.33.dist-info/METADATA
quantbacktest-0.0.33.dist-info/WHEEL
quantbacktest-0.0.33.dist-info/entry_points.txt
quantbacktest-0.0.33.dist-info/top_level.txt
quantbacktest-0.0.33.dist-info/RECORD
