Metadata-Version: 2.1
Name: quantbacktest
Version: 0.0.33
Summary: This backtesting is used to backtest algorithmic/quant trading strategies.
Home-page: https://gitlab.com/fsbc/theses/quantbacktest
Author: Jan Frederic Spörer
Author-email: jan.spoerer@whu.edu
License: BSD two-clause license
Platform: UNKNOWN
